TkinterLite/__init__.py
TkinterLite/easy_auto_window.py
TkinterLite/easy_auto_window_size.py
TkinterLite/easy_button.py
TkinterLite/easy_check_button.py
TkinterLite/easy_drop_list.py
TkinterLite/easy_fade_animation.py
TkinterLite/easy_frame.py
TkinterLite/easy_label.py
TkinterLite/easy_mobile_animation.py
TkinterLite/easy_multi_text.py
TkinterLite/easy_picture.py
TkinterLite/easy_popup_animation.py
TkinterLite/easy_progressbar.py
TkinterLite/easy_radio_button.py
TkinterLite/easy_scale.py
TkinterLite/easy_spinbox.py
TkinterLite/easy_text.py
TkinterLite/easy_warning_windows.py
TkinterLite/test.py
tkinterlite-3.2.2.dist-info/licenses/LICENSE
tkinterlite-3.2.2.dist-info/METADATA
tkinterlite-3.2.2.dist-info/WHEEL
tkinterlite-3.2.2.dist-info/top_level.txt
tkinterlite-3.2.2.dist-info/RECORD
