Metadata-Version: 2.4
Name: TkinterLite
Version: 3.2.2
Summary: tkinter库的简化版
Home-page: https://github.com/Yanxinle1123/LeleEasyTkinter
Author: YanXinle
Author-email: 1020121123@qq.com
License-File: LICENSE
Requires-Dist: future~=1.0.0
Requires-Dist: pillow~=11.3.0
Requires-Dist: PyQt5~=5.15.11
Requires-Dist: setuptools~=78.1.1
Dynamic: author
Dynamic: author-email
Dynamic: home-page
Dynamic: license-file
Dynamic: requires-dist
Dynamic: summary
